ann2pmml/__init__.py
ann2pmml-1.0.2.dist-info/LICENSE
ann2pmml-1.0.2.dist-info/METADATA
ann2pmml-1.0.2.dist-info/WHEEL
ann2pmml-1.0.2.dist-info/top_level.txt
ann2pmml-1.0.2.dist-info/RECORD
