Metadata-Version: 2.1
Name: ann2pmml
Version: 1.0.2
Summary: Auto PMML Exporter of Nerual Network Models.
Home-page: https://github.com/lampda/ANN2PMML
Author: lampda
Author-email: saintree@gmail.com
License: MIT
Platform: UNKNOWN
Classifier: Intended Audience :: Science/Research
Classifier: Intended Audience :: Developers
Classifier: Development Status :: 3 - Alpha
Classifier: Operating System :: OS Independent
Classifier: Programming Language :: Python
Classifier: Programming Language :: Python :: 3 :: Only
Classifier: Topic :: Software Development :: Libraries
Classifier: Topic :: Software Development :: Libraries :: Python Modules
Requires-Dist: numpy (>=1.6.1)
Requires-Dist: SciPy (>=0.9)
Requires-Dist: tensorflow (>=1.12.0)
Requires-Dist: keras (<=2.3.1,>=1.0.6)
Requires-Dist: scikit-learn (>=0.22)
